welchsPSD/__init__.py
welchsPSD/welchsPSD.py
welchsPSD-0.1.0.dist-info/METADATA
welchsPSD-0.1.0.dist-info/WHEEL
welchsPSD-0.1.0.dist-info/top_level.txt
welchsPSD-0.1.0.dist-info/RECORD
