Metadata-Version: 2.1
Name: welchsPSD
Version: 0.1.0
Summary: A Python library for calculating welchsPSD
Home-page: https://github.com/Metaverse-Crowdsource/EEG-Chaos-Kuramoto-Neural-Net/blob/main/Spectral%20Analysis/Spectral%20Analysis.ipynb
Author: soul_syrup
Author-email: soul.syrupp@gmail.com
Requires-Dist: numpy
